connectlife_cloud-0.3.1.dist-info/licenses/LICENSE
devices/__init__.py
devices/atw_035_699.py
devices/base.py
devices/base_bean.py
devices/bean_006_299.py
devices/hum_007.py
devices/split_ac_009_199.py
devices/window_ac_008_399.py
connectlife_cloud-0.3.1.dist-info/METADATA
connectlife_cloud-0.3.1.dist-info/WHEEL
connectlife_cloud-0.3.1.dist-info/top_level.txt
connectlife_cloud-0.3.1.dist-info/RECORD
