Metadata-Version: 2.4
Name: connectlife-cloud
Version: 0.3.1
Summary: ConnectLife Cloud API client library for Home Assistant integrations
Home-page: https://github.com/Connectlife-LLC/connectlife-cloud
Author: ConnectLife LLC
Author-email: ConnectLife LLC <support@connectlife.com>
License: MIT
Project-URL: Homepage, https://github.com/Connectlife-LLC/connectlife-cloud
Project-URL: Repository, https://github.com/Connectlife-LLC/connectlife-cloud
Project-URL: Issues, https://github.com/Connectlife-LLC/connectlife-cloud/issues
Keywords: homeassistant,connectlife,api,client,iot
Classifier: Development Status :: 4 - Beta
Classifier: Intended Audience :: Developers
Classifier: License :: OSI Approved :: MIT License
Classifier: Operating System :: OS Independent
Classifier: Programming Language :: Python :: 3
Classifier: Programming Language :: Python :: 3.8
Classifier: Programming Language :: Python :: 3.9
Classifier: Programming Language :: Python :: 3.10
Classifier: Programming Language :: Python :: 3.11
Classifier: Programming Language :: Python :: 3.12
Classifier: Topic :: Home Automation
Classifier: Topic :: Software Development :: Libraries :: Python Modules
Requires-Python: >=3.8
License-File: LICENSE
Requires-Dist: aiohttp>=3.8.0
Requires-Dist: pytz>=2021.1
Provides-Extra: dev
Requires-Dist: pytest>=6.0; extra == "dev"
Requires-Dist: pytest-asyncio>=0.18.0; extra == "dev"
Requires-Dist: pytest-cov>=2.10.0; extra == "dev"
Requires-Dist: black>=21.0.0; extra == "dev"
Requires-Dist: isort>=5.0.0; extra == "dev"
Requires-Dist: mypy>=0.910; extra == "dev"
Requires-Dist: pre-commit>=2.15.0; extra == "dev"
Dynamic: author
Dynamic: home-page
Dynamic: license-file
Dynamic: requires-python
